mmhelloworld.py
mmhelloworld-0.0.3.dist-info/LICENSE
mmhelloworld-0.0.3.dist-info/METADATA
mmhelloworld-0.0.3.dist-info/WHEEL
mmhelloworld-0.0.3.dist-info/top_level.txt
mmhelloworld-0.0.3.dist-info/RECORD
