Metadata-Version: 2.1
Name: mmhelloworld
Version: 0.0.3
Summary: Say Hello!
Home-page: https://github.com/manasm11/mmhelloworld.git
Author: Manas Mishra
Author-email: manas.m22@gmail.com
License: UNKNOWN
Platform: UNKNOWN
Classifier: Programming Language :: Python :: 3
Classifier: Programming Language :: Python :: 3.6
Classifier: Programming Language :: Python :: 3.7
Classifier: License :: OSI Approved :: MIT License
Classifier: Operating System :: OS Independent
Requires-Dist: blessings (~=1.7)
Provides-Extra: admin
Requires-Dist: black ; extra == 'admin'
Requires-Dist: pytest (>=3.7) ; extra == 'admin'
Requires-Dist: twine ; extra == 'admin'
Requires-Dist: wheel ; extra == 'admin'
Provides-Extra: dev
Requires-Dist: black ; extra == 'dev'
Requires-Dist: pytest (>=3.7) ; extra == 'dev'
Requires-Dist: wheel ; extra == 'dev'
